petsird/__init__.py
petsird/_binary.py
petsird/_dtypes.py
petsird/_ndjson.py
petsird/binary.py
petsird/ndjson.py
petsird/protocols.py
petsird/types.py
petsird/version.py
petsird/yardl_types.py
petsird/helpers/__init__.py
petsird/helpers/analysis.py
petsird/helpers/generator.py
petsird/helpers/geometry.py
petsird/helpers/plot_scanner.py
petsird-0.8.1.dist-info/licenses/LICENSE
petsird-0.8.1.dist-info/METADATA
petsird-0.8.1.dist-info/WHEEL
petsird-0.8.1.dist-info/top_level.txt
petsird-0.8.1.dist-info/RECORD
