Metadata-Version: 2.4
Name: petsird
Version: 0.8.1
Summary: Library and tools for working with Positron Emission Tomography Standardization Initiative Raw Data (PETSIRD)
Author-email: Kris Thielemans <k.thielemans@ucl.ac.uk>
Maintainer-email: Casper da Costa-Luis <imaging@cdcl.ml>, Kris Thielemans <k.thielemans@ucl.ac.uk>
License-Expression: Apache-2.0
Project-URL: Homepage, https://etsinitiative.org
Project-URL: Repository, https://github.com/ETSInitiative/PETSIRD
Project-URL: Issues, https://github.com/ETSInitiative/PETSIRD/issues
Classifier: Development Status :: 3 - Alpha
Classifier: Operating System :: OS Independent
Classifier: Programming Language :: Python :: 3
Classifier: Programming Language :: Python :: 3.9
Classifier: Programming Language :: Python :: 3.10
Classifier: Programming Language :: Python :: 3.11
Classifier: Programming Language :: Python :: 3.12
Classifier: Programming Language :: Python :: 3 :: Only
Classifier: Intended Audience :: Science/Research
Classifier: Topic :: Scientific/Engineering :: Medical Science Apps.
Requires-Python: >=3.9
License-File: LICENSE
Requires-Dist: numpy>=1.22
Dynamic: license-file
